api_exception/__init__.py
api_exception/__main__.py
api_exception/enums.py
api_exception/exception.py
api_exception/logger.py
api_exception/py.typed
api_exception/response_model.py
api_exception/response_utils.py
api_exception/rfc7807_model.py
apiexception-0.2.3.dist-info/METADATA
apiexception-0.2.3.dist-info/WHEEL
apiexception-0.2.3.dist-info/entry_points.txt
apiexception-0.2.3.dist-info/licenses/LICENCE.txt
apiexception-0.2.3.dist-info/RECORD
