Metadata-Version: 2.4
Name: apiexception
Version: 0.2.3
Summary: Consistent JSON response formatting and exception & error handling for FastAPI applications
License: MIT
License-File: LICENCE.txt
Keywords: fastapi,exception,error-handling,json-response
Author: Ahmet Kutay URAL
Author-email: ahmetkutayural@gmail.com
Requires-Python: >=3.9,<4.0
Classifier: Development Status :: 5 - Production/Stable
Classifier: Environment :: Web Environment
Classifier: Framework :: FastAPI
Classifier: Intended Audience :: Developers
Classifier: License :: OSI Approved :: MIT License
Classifier: Operating System :: OS Independent
Classifier: Programming Language :: Python
Classifier: Programming Language :: Python :: 3
Classifier: Programming Language :: Python :: 3.9
Classifier: Programming Language :: Python :: 3.10
Classifier: Programming Language :: Python :: 3.11
Classifier: Programming Language :: Python :: 3.12
Classifier: Programming Language :: Python :: 3.13
Classifier: Programming Language :: Python :: 3.14
Classifier: Topic :: Software Development :: Libraries :: Application Frameworks
Classifier: Topic :: Software Development :: Libraries :: Python Modules
Classifier: Typing :: Typed
Requires-Dist: click (>=8.0.0)
Requires-Dist: fastapi (>=0.115.4)
Requires-Dist: httpx (>=0.27.0)
Requires-Dist: pydantic (>=2.0.0)
Requires-Dist: typing-extensions (>=4.0.0)
Project-URL: Bug Tracker, https://github.com/akutayural/APIException/issues
Project-URL: Changelog, https://github.com/akutayural/APIException/blob/main/docs/changelog.md
Project-URL: Documentation, https://akutayural.github.io/APIException/
Project-URL: Source, https://github.com/akutayural/APIException
